{"as_of":"2026-07-13T08:33:42+00:00","ts":1783931622,"n":44,"quotes":{"asml":{"price_eur":1548.4,"change_pct":-1.55,"market_cap_eur":596780721896,"currency":"EUR","ts":1783931604},"asm-international":{"price_eur":897.4,"change_pct":-1.9,"market_cap_eur":43870360412,"currency":"EUR","ts":1783931604},"besi":{"price_eur":251.4,"change_pct":-1.49,"market_cap_eur":19907901432,"currency":"EUR","ts":1783931605},"aixtron":{"price_eur":43.67,"change_pct":-0.09,"market_cap_eur":4925358212,"currency":"EUR","ts":1783931605},"soitec":{"price_eur":98.98,"change_pct":1.31,"market_cap_eur":3537916594,"currency":"EUR","ts":1783931606},"siltronic":{"price_eur":91.8,"change_pct":3.55,"market_cap_eur":2754000092,"currency":"EUR","ts":1783931606},"pva-tepla":{"price_eur":39.34,"change_pct":-0.71,"market_cap_eur":803424694,"currency":"EUR","ts":1783931606},"lpkf":{"price_eur":17.1,"change_pct":-2.84,"market_cap_eur":418890946,"currency":"EUR","ts":1783931607},"stmicroelectronics":{"price_eur":61.7,"change_pct":-0.64,"market_cap_eur":55061069390,"currency":"EUR","ts":1783931607},"infineon":{"price_eur":71.31,"change_pct":-1.48,"market_cap_eur":92667317511,"currency":"EUR","ts":1783931608},"nxp":{"price_eur":255.4352,"change_pct":-0.25,"market_cap_eur":64490010506,"currency":"USD","ts":1783931608},"x-fab":{"price_eur":7.99,"change_pct":2.7,"market_cap_eur":1043749027,"currency":"EUR","ts":1783931608},"nordic-semiconductor":{"price_eur":14.9071,"change_pct":-1.01,"market_cap_eur":2943560651,"currency":"NOK","ts":1783931609},"melexis":{"price_eur":76.0,"change_pct":5.12,"market_cap_eur":2992667884,"currency":"EUR","ts":1783931609},"ovhcloud":{"price_eur":14.7,"change_pct":0.68,"market_cap_eur":2197393133,"currency":"EUR","ts":1783931610},"ionos":{"price_eur":29.68,"change_pct":4.07,"market_cap_eur":4061608287,"currency":"EUR","ts":1783931610},"atos":{"price_eur":33.02,"change_pct":-0.06,"market_cap_eur":641000561,"currency":"EUR","ts":1783931611},"at-and-s":{"price_eur":180.4,"change_pct":-3.74,"market_cap_eur":7008539763,"currency":"EUR","ts":1783931611},"suss-microtec":{"price_eur":86.35,"change_pct":1.47,"market_cap_eur":1650626677,"currency":"EUR","ts":1783931611},"jenoptik":{"price_eur":41.44,"change_pct":0.48,"market_cap_eur":2371947407,"currency":"EUR","ts":1783931612},"elmos-semiconductor":{"price_eur":166.8,"change_pct":-1.65,"market_cap_eur":2873119544,"currency":"EUR","ts":1783931612},"ams-osram":{"price_eur":20.3406,"change_pct":-0.21,"market_cap_eur":2024695048,"currency":"CHF","ts":1783931613},"cancom":{"price_eur":23.4,"change_pct":0.65,"market_cap_eur":672509039,"currency":"EUR","ts":1783931613},"northern-data":{"price_eur":7.44,"change_pct":-2.36,"market_cap_eur":477623281,"currency":"EUR","ts":1783931614},"lighton":{"price_eur":5.78,"change_pct":-3.67,"market_cap_eur":42057501,"currency":"EUR","ts":1783931614},"qt-group":{"price_eur":23.88,"change_pct":-0.83,"market_cap_eur":606342097,"currency":"EUR","ts":1783931614},"schneider-electric":{"price_eur":267.85,"change_pct":-0.13,"market_cap_eur":150610963461,"currency":"EUR","ts":1783931615},"siemens-energy":{"price_eur":152.3,"change_pct":0.16,"market_cap_eur":129584239351,"currency":"EUR","ts":1783931615},"kalray":{"price_eur":8.58,"change_pct":-1.94,"market_cap_eur":132649690,"currency":"EUR","ts":1783931615},"psi-software":{"price_eur":45.0,"change_pct":-3.02,"market_cap_eur":701831745,"currency":"EUR","ts":1783931616},"nebius-group":{"price_eur":191.9741,"change_pct":-0.13,"market_cap_eur":48741874187,"currency":"USD","ts":1783931616},"technoprobe":{"price_eur":31.54,"change_pct":-1.19,"market_cap_eur":20195672822,"currency":"EUR","ts":1783931617},"adyen":{"price_eur":848.7,"change_pct":-0.18,"market_cap_eur":26765190885,"currency":"EUR","ts":1783931617},"bechtle":{"price_eur":30.68,"change_pct":0.26,"market_cap_eur":3865680038,"currency":"EUR","ts":1783931617},"capgemini":{"price_eur":90.1,"change_pct":1.03,"market_cap_eur":14930490029,"currency":"EUR","ts":1783931618},"deutsche-telekom":{"price_eur":26.74,"change_pct":2.49,"market_cap_eur":129368718403,"currency":"EUR","ts":1783931618},"scout24":{"price_eur":74.1,"change_pct":1.44,"market_cap_eur":5240017108,"currency":"EUR","ts":1783931619},"nexi":{"price_eur":3.933,"change_pct":-0.15,"market_cap_eur":4611509377,"currency":"EUR","ts":1783931619},"nokia":{"price_eur":10.925,"change_pct":0.28,"market_cap_eur":60989186883,"currency":"EUR","ts":1783931619},"octave-intelligence":{"price_eur":14.6576,"change_pct":-0.92,"market_cap_eur":null,"currency":"SEK","ts":1783931620},"orange":{"price_eur":16.145,"change_pct":1.73,"market_cap_eur":42909687146,"currency":"EUR","ts":1783931621},"reply":{"price_eur":96.1,"change_pct":1.37,"market_cap_eur":3510665754,"currency":"EUR","ts":1783931621},"telenor":{"price_eur":13.0459,"change_pct":0.9,"market_cap_eur":17805956946,"currency":"NOK","ts":1783931621},"vend-marketplaces":{"price_eur":21.8506,"change_pct":0.58,"market_cap_eur":4469301645,"currency":"NOK","ts":1783931622}}}